record_kit/__init__.py
record_kit/parser.py
record_kit/recorder.py
record_kit-0.1.10.dist-info/LICENSE
record_kit-0.1.10.dist-info/METADATA
record_kit-0.1.10.dist-info/WHEEL
record_kit-0.1.10.dist-info/top_level.txt
record_kit-0.1.10.dist-info/RECORD
