Metadata-Version: 2.1
Name: record-kit
Version: 0.1.10
Summary: A simple record toolkit generating human readable data record for experiment
Home-page: https://github.com/actcwlf/record-kit
Author: actcwlf
Author-email: actcwlf@qq.com
License: MIT
Classifier: Development Status :: 1 - Planning
Classifier: Intended Audience :: Developers
Classifier: Intended Audience :: End Users/Desktop
Classifier: License :: OSI Approved :: MIT License
Classifier: Programming Language :: Python :: 3 :: Only
Classifier: Programming Language :: Python :: 3.6
Classifier: Programming Language :: Python :: 3.7
Classifier: Programming Language :: Python :: 3.8
Classifier: Topic :: Software Development
Requires-Python: >=3.6
License-File: LICENSE
Requires-Dist: pandas (>=0.24.1)
Requires-Dist: Markdown (>=3.3.0)
